krystof2h_test/__init__.py
krystof2h_test/hello_world.py
krystof2h_test-0.0.4.dist-info/METADATA
krystof2h_test-0.0.4.dist-info/WHEEL
krystof2h_test-0.0.4.dist-info/top_level.txt
krystof2h_test-0.0.4.dist-info/RECORD
