Metadata-Version: 2.1
Name: krystof2h_test
Version: 0.0.4
Requires-Dist: requests
